[
  {
    "_id": "5fccb8dfd49561453bf5eea3",
    "index": 0,
    "guid": "969103e9-4427-409b-8fe7-b2ddb59faa03",
    "isActive": false,
    "balance": "$1,082.07",
    "picture": "http://placehold.it/32x32",
    "age": 23,
    "eyeColor": "green",
    "name": "Marsh Whitfield",
    "gender": "male",
    "company": "SONIQUE",
    "email": "marshwhitfield@sonique.com",
    "phone": "+1 (914) 533-2842",
    "address": "785 McKibben Street, Richmond, Maine, 4260",
    "about": "Incididunt esse sint fugiat consectetur proident eu excepteur veniam irure. Non anim cupidatat adipisicing non occaecat sit enim fugiat sit non. Eu consectetur nostrud in laborum exercitation deserunt enim nostrud non dolor. Cillum veniam nisi aliquip pariatur dolor est. Enim id tempor laboris amet cupidatat velit elit cupidatat sit velit laboris. Sit et sunt fugiat ut. Culpa laboris excepteur Lorem ea.\r\n",
    "registered": "2014-02-12T08:28:46 +05:00",
    "latitude": 47.727991,
    "longitude": 12.924143,
    "tags": [
      "do",
      "aliquip",
      "aliquip",
      "eiusmod",
      "minim",
      "ad",
      "commodo"
    ],
    "friends": [
      {
        "id": 0,
        "name": "Maryanne Kelley"
      },
      {
        "id": 1,
        "name": "Hewitt Beard"
      },
      {
        "id": 2,
        "name": "Beck Noel"
      }
    ],
    "greeting": "Hello, Marsh Whitfield! You have 8 unread messages.",
    "favoriteFruit": "apple"
  },
  {
    "_id": "5fccb8df535d27fb9da38aa7",
    "index": 1,
    "guid": "98084d34-2066-416f-8cb8-6d086f923e3c",
    "isActive": true,
    "balance": "$3,317.34",
    "picture": "http://placehold.it/32x32",
    "age": 36,
    "eyeColor": "blue",
    "name": "Schmidt Hale",
    "gender": "male",
    "company": "DEEPENDS",
    "email": "schmidthale@deepends.com",
    "phone": "+1 (860) 408-3793",
    "address": "147 Varet Street, Maury, Montana, 517",
    "about": "In commodo sit irure ex consectetur velit pariatur. Enim adipisicing sit veniam incididunt mollit tempor. Voluptate proident exercitation magna cupidatat et excepteur laboris Lorem labore tempor proident qui et. Sint amet ipsum ut qui cupidatat dolore in cupidatat. Nulla magna ipsum ea cillum quis deserunt labore fugiat fugiat ut nostrud voluptate deserunt fugiat.\r\n",
    "registered": "2017-06-13T01:22:49 +04:00",
    "latitude": 54.760294,
    "longitude": -34.0279,
    "tags": [
      "voluptate",
      "cillum",
      "dolore",
      "laborum",
      "Lorem",
      "commodo",
      "cillum"
    ],
    "friends": [
      {
        "id": 0,
        "name": "Debra Wilder"
      },
      {
        "id": 1,
        "name": "Ball Moody"
      },
      {
        "id": 2,
        "name": "Carissa Workman"
      }
    ],
    "greeting": "Hello, Schmidt Hale! You have 5 unread messages.",
    "favoriteFruit": "strawberry"
  },
  {
    "_id": "5fccb8dfa7710d5959256264",
    "index": 2,
    "guid": "52709055-c3dd-431e-b33e-d893a4ef92fa",
    "isActive": true,
    "balance": "$2,944.24",
    "picture": "http://placehold.it/32x32",
    "age": 25,
    "eyeColor": "green",
    "name": "Delgado Franco",
    "gender": "male",
    "company": "NAVIR",
    "email": "delgadofranco@navir.com",
    "phone": "+1 (981) 413-2446",
    "address": "789 Dunham Place, Lisco, Nebraska, 6777",
    "about": "Magna est dolore proident enim in velit commodo do sint. Duis minim ut et do culpa laborum anim quis ad officia et. Commodo et ad laborum cillum deserunt do excepteur in reprehenderit sit minim fugiat. Adipisicing non ex est amet duis. Eu dolor excepteur occaecat ullamco in. Magna voluptate ut cillum in pariatur nulla velit laboris ea aute ex sit. Nostrud dolor do sunt laborum magna ex ex excepteur amet sunt non cupidatat.\r\n",
    "registered": "2018-08-19T03:04:02 +04:00",
    "latitude": -58.801733,
    "longitude": 52.997521,
    "tags": [
      "consectetur",
      "dolor",
      "dolore",
      "voluptate",
      "veniam",
      "veniam",
      "veniam"
    ],
    "friends": [
      {
        "id": 0,
        "name": "Mack Anderson"
      },
      {
        "id": 1,
        "name": "Wolfe Stein"
      },
      {
        "id": 2,
        "name": "Irwin Bernard"
      }
    ],
    "greeting": "Hello, Delgado Franco! You have 5 unread messages.",
    "favoriteFruit": "apple"
  },
  {
    "_id": "5fccb8df501b972bb2f42f74",
    "index": 3,
    "guid": "fbbdd5da-2730-415f-bf70-49a7905c4f61",
    "isActive": false,
    "balance": "$3,945.30",
    "picture": "http://placehold.it/32x32",
    "age": 23,
    "eyeColor": "brown",
    "name": "Patel Joyce",
    "gender": "male",
    "company": "NETUR",
    "email": "pateljoyce@netur.com",
    "phone": "+1 (884) 580-3515",
    "address": "692 Chapel Street, Bynum, Illinois, 1759",
    "about": "Proident aute quis quis enim elit. Consequat adipisicing reprehenderit eiusmod commodo. Minim culpa aliqua pariatur ad do nostrud fugiat consequat do dolore nulla aute consectetur mollit. Duis non culpa do deserunt. Et occaecat minim amet aliqua qui proident incididunt ut. Enim cupidatat dolor occaecat aute ex laboris aute laborum reprehenderit laboris proident. Dolor eu reprehenderit consequat voluptate Lorem adipisicing incididunt id labore occaecat ullamco ex deserunt non.\r\n",
    "registered": "2019-03-08T03:42:15 +05:00",
    "latitude": 85.994406,
    "longitude": 97.826558,
    "tags": [
      "veniam",
      "dolore",
      "deserunt",
      "esse",
      "consequat",
      "sunt",
      "occaecat"
    ],
    "friends": [
      {
        "id": 0,
        "name": "Kerr Keith"
      },
      {
        "id": 1,
        "name": "Frederick Good"
      },
      {
        "id": 2,
        "name": "Keisha Norton"
      }
    ],
    "greeting": "Hello, Patel Joyce! You have 7 unread messages.",
    "favoriteFruit": "banana"
  },
  {
    "_id": "5fccb8df122c5aeed50574c1",
    "index": 4,
    "guid": "bd72f4e4-8098-4bf8-83a0-02306dfd387a",
    "isActive": false,
    "balance": "$1,777.45",
    "picture": "http://placehold.it/32x32",
    "age": 30,
    "eyeColor": "brown",
    "name": "Susanna Camacho",
    "gender": "female",
    "company": "VOLAX",
    "email": "susannacamacho@volax.com",
    "phone": "+1 (823) 485-3682",
    "address": "972 Williams Place, Fannett, Northern Mariana Islands, 8454",
    "about": "Non deserunt culpa ut duis occaecat do in duis eu mollit esse ex consequat laborum. Ea cillum aute reprehenderit fugiat incididunt qui consectetur. Commodo culpa sunt adipisicing quis fugiat amet eiusmod. Minim aute sunt consectetur nulla non reprehenderit. Eiusmod magna consectetur culpa culpa nisi. Officia consequat exercitation aute tempor.\r\n",
    "registered": "2020-05-21T09:44:59 +04:00",
    "latitude": 10.306444,
    "longitude": -113.254582,
    "tags": [
      "officia",
      "labore",
      "exercitation",
      "enim",
      "exercitation",
      "nisi",
      "occaecat"
    ],
    "friends": [
      {
        "id": 0,
        "name": "Lucia Cannon"
      },
      {
        "id": 1,
        "name": "Deidre Bowen"
      },
      {
        "id": 2,
        "name": "Giles Ellis"
      }
    ],
    "greeting": "Hello, Susanna Camacho! You have 2 unread messages.",
    "favoriteFruit": "strawberry"
  },
  {
    "_id": "5fccb8df1d23f306582af649",
    "index": 5,
    "guid": "1da84a20-9cc8-4234-8526-224da3acbaee",
    "isActive": false,
    "balance": "$2,758.66",
    "picture": "http://placehold.it/32x32",
    "age": 39,
    "eyeColor": "brown",
    "name": "Eliza Dennis",
    "gender": "female",
    "company": "ISOSWITCH",
    "email": "elizadennis@isoswitch.com",
    "phone": "+1 (902) 477-3960",
    "address": "197 Sedgwick Place, Tuttle, Mississippi, 5750",
    "about": "Sit ipsum non pariatur nulla est sint eu deserunt ea. Cillum labore enim et tempor ullamco reprehenderit. Dolor consequat aliqua adipisicing nulla ullamco incididunt ut excepteur cillum aliquip aliquip duis officia velit. Voluptate officia sunt in Lorem. Consectetur occaecat deserunt pariatur voluptate. Magna ipsum mollit aliqua reprehenderit est ea reprehenderit ipsum laborum laboris reprehenderit magna.\r\n",
    "registered": "2016-09-04T04:40:24 +04:00",
    "latitude": 18.653048,
    "longitude": -156.502186,
    "tags": [
      "dolor",
      "tempor",
      "nostrud",
      "commodo",
      "anim",
      "ut",
      "eu"
    ],
    "friends": [
      {
        "id": 0,
        "name": "Rita Kennedy"
      },
      {
        "id": 1,
        "name": "Selena Sykes"
      },
      {
        "id": 2,
        "name": "Maryellen Cummings"
      }
    ],
    "greeting": "Hello, Eliza Dennis! You have 2 unread messages.",
    "favoriteFruit": "apple"
  },
  {
    "_id": "5fccb8dfe1aae5baef84ffd5",
    "index": 6,
    "guid": "62bdbbe0-698c-4cd9-ba4c-e8d61ff4f4b4",
    "isActive": false,
    "balance": "$2,723.15",
    "picture": "http://placehold.it/32x32",
    "age": 21,
    "eyeColor": "blue",
    "name": "Muriel Rowe",
    "gender": "female",
    "company": "GENMEX",
    "email": "murielrowe@genmex.com",
    "phone": "+1 (908) 490-2374",
    "address": "886 Brooklyn Avenue, Shasta, Hawaii, 7531",
    "about": "Exercitation do anim deserunt voluptate adipisicing laboris sunt non fugiat. Et dolor eiusmod occaecat labore irure ut occaecat ut eiusmod et duis. Aliqua ipsum id sunt eu in exercitation enim deserunt. Consequat dolor cillum esse dolor reprehenderit esse duis ut. Lorem velit est occaecat commodo deserunt quis sit do eu id cillum aliquip amet proident.\r\n",
    "registered": "2014-07-26T05:26:53 +04:00",
    "latitude": 51.756701,
    "longitude": 19.624375,
    "tags": [
      "mollit",
      "pariatur",
      "dolore",
      "exercitation",
      "quis",
      "nostrud",
      "quis"
    ],
    "friends": [
      {
        "id": 0,
        "name": "Gretchen Torres"
      },
      {
        "id": 1,
        "name": "Wilda Talley"
      },
      {
        "id": 2,
        "name": "Christian Delacruz"
      }
    ],
    "greeting": "Hello, Muriel Rowe! You have 2 unread messages.",
    "favoriteFruit": "strawberry"
  }
]